pytemplates_typer_cli/__init__.py
pytemplates_typer_cli/__version__.py
pytemplates_typer_cli/core/__init__.py
pytemplates_typer_cli/core/module1.py
pytemplates_typer_cli/core/module2.py
pytemplates_typer_cli/main.py
pytemplates_typer_cli-0.1.1.dist-info/entry_points.txt
pytemplates_typer_cli-0.1.1.dist-info/LICENSE
pytemplates_typer_cli-0.1.1.dist-info/WHEEL
pytemplates_typer_cli-0.1.1.dist-info/METADATA
pytemplates_typer_cli-0.1.1.dist-info/RECORD
