Metadata-Version: 2.1
Name: pytemplates-typer-cli
Version: 0.1.1
Summary: A production ready python CLI template.
Home-page: https://github.com/PyTemplate/typer_cli
License: MIT
Author: crabtr26
Author-email: crabtr26@gmail.com
Requires-Python: >=3.8,<4.0
Classifier: Development Status :: 2 - Pre-Alpha
Classifier: Intended Audience :: Developers
Classifier: License :: OSI Approved :: MIT License
Classifier: Natural Language :: English
Classifier: Programming Language :: Python :: 3
Classifier: Programming Language :: Python :: 3.10
Classifier: Programming Language :: Python :: 3.8
Classifier: Programming Language :: Python :: 3.9
Provides-Extra: dev
Provides-Extra: docs
Provides-Extra: lint
Provides-Extra: test
Requires-Dist: black (>=22.3.0,<23.0.0); extra == "lint" or extra == "dev"
Requires-Dist: bump2version (>=1.0.1,<2.0.0); extra == "dev"
Requires-Dist: flake8 (>=4.0.1,<5.0.0); extra == "lint" or extra == "dev"
Requires-Dist: isort (>=5.10.1,<6.0.0); extra == "lint" or extra == "dev"
Requires-Dist: mkdocs (>=1.3.0,<2.0.0); extra == "docs" or extra == "dev"
Requires-Dist: mkdocs-material (>=8.3.9,<9.0.0); extra == "docs" or extra == "dev"
Requires-Dist: mkdocstrings (>=0.19.0,<0.20.0); extra == "docs" or extra == "dev"
Requires-Dist: mkdocstrings-python (>=0.7.1,<0.8.0); extra == "docs" or extra == "dev"
Requires-Dist: mypy (>=0.961,<0.962); extra == "lint" or extra == "dev"
Requires-Dist: pre-commit (>=2.19.0,<3.0.0); extra == "lint" or extra == "dev"
Requires-Dist: pylint (>=2.13.8,<3.0.0); extra == "lint" or extra == "dev"
Requires-Dist: pytest (>=7.1.2,<8.0.0); extra == "test" or extra == "dev"
Requires-Dist: pytest-cov (>=3.0.0,<4.0.0); extra == "test" or extra == "dev"
Requires-Dist: typer (>=0.4.1,<0.5.0)
Project-URL: Repository, https://github.com/PyTemplate/typer_cli
